README.md
setup.cfg
setup.py
pyAHP.egg-info/PKG-INFO
pyAHP.egg-info/SOURCES.txt
pyAHP.egg-info/dependency_links.txt
pyAHP.egg-info/requires.txt
pyAHP.egg-info/top_level.txt
pyahp/__init__.py
pyahp/__main__.py
pyahp/errors.py
pyahp/parser.py
pyahp/utils.py
pyahp/hierarchy/__init__.py
pyahp/hierarchy/ahpcriterion.py
pyahp/hierarchy/ahpmodel.py
pyahp/methods/__init__.py
pyahp/methods/approximate.py
pyahp/methods/eigenvalue.py
pyahp/methods/geometric.py
pyahp/methods/method.py