Metadata-Version: 1.2
Name: pyAHP
Version: 0.1.2
Summary: Analytic Hierarchy Process solver
Home-page: https://github.com/pyAHP/pyAHP
Author: Abhinav Mishra
Author-email: mishrabhinav96@gmail.com
License: MIT
Keywords: ahp analytic hierarchy process
Platform: UNKNOWN
Requires-Python: >=3
